odoo/addons/easy_my_coop_eater/__init__.py
odoo/addons/easy_my_coop_eater/__manifest__.py
odoo/addons/easy_my_coop_eater/models/__init__.py
odoo/addons/easy_my_coop_eater/models/coop.py
odoo/addons/easy_my_coop_eater/models/product.py
odoo/addons/easy_my_coop_eater/view/product_view.xml
odoo12_addon_easy_my_coop_eater-12.0.1.0.0.99.dev1.dist-info/METADATA
odoo12_addon_easy_my_coop_eater-12.0.1.0.0.99.dev1.dist-info/WHEEL
odoo12_addon_easy_my_coop_eater-12.0.1.0.0.99.dev1.dist-info/top_level.txt
odoo12_addon_easy_my_coop_eater-12.0.1.0.0.99.dev1.dist-info/RECORD
